setup.cfg
setup.py
dm/__init__.py
dm.saml2.egg-info/PKG-INFO
dm.saml2.egg-info/SOURCES.txt
dm.saml2.egg-info/dependency_links.txt
dm.saml2.egg-info/namespace_packages.txt
dm.saml2.egg-info/not-zip-safe
dm.saml2.egg-info/requires.txt
dm.saml2.egg-info/top_level.txt
dm/saml2/LICENSE.txt
dm/saml2/README.txt
dm/saml2/VERSION.txt
dm/saml2/__init__.py
dm/saml2/compat.py
dm/saml2/config.py
dm/saml2/metadata.py
dm/saml2/signature.py
dm/saml2/util.py
dm/saml2/uuid.py
dm/saml2/binding/__init__.py
dm/saml2/binding/compat.py
dm/saml2/binding/httpartifact.py
dm/saml2/binding/httppost.py
dm/saml2/binding/httpredirect.py
dm/saml2/binding/soap.py
dm/saml2/binding/util.py
dm/saml2/binding/tests/__init__.py
dm/saml2/binding/tests/base.py
dm/saml2/binding/tests/signature.py
dm/saml2/binding/tests/test_httpartifact.py
dm/saml2/binding/tests/test_httppost.py
dm/saml2/binding/tests/test_httpredirect.py
dm/saml2/binding/tests/test_soap.py
dm/saml2/pyxb/__init__.py
dm/saml2/pyxb/assertion.py
dm/saml2/pyxb/authncontext.py
dm/saml2/pyxb/authncontext_ip.py
dm/saml2/pyxb/authncontext_ippword.py
dm/saml2/pyxb/authncontext_ppt.py
dm/saml2/pyxb/gen.sh
dm/saml2/pyxb/metadata.py
dm/saml2/pyxb/protocol.py
dm/saml2/pyxb/modschema/README.txt
dm/saml2/pyxb/modschema/saml-schema-authn-context-ip-2.0.xsd
dm/saml2/pyxb/modschema/saml-schema-authn-context-ippword-2.0.xsd
dm/saml2/pyxb/modschema/saml-schema-authn-context-ppt-2.0.xsd
dm/saml2/pyxb/modschema/saml-schema-authn-context-pword-2.0.xsd
dm/saml2/pyxb/modschema/saml-schema-authn-context-session-2.0.xsd
dm/saml2/pyxb/modschema/saml-schema-authn-context-types-2.0.xsd
dm/saml2/pyxb/raw/__init__.py
dm/saml2/pyxb/raw/authncontext.py
dm/saml2/pyxb/raw/authncontext.wxs
dm/saml2/pyxb/raw/authncontext_ip.py
dm/saml2/pyxb/raw/authncontext_ippword.py
dm/saml2/pyxb/raw/authncontext_ppt.py