Metadata-Version: 1.1
Name: dm.saml2
Version: 3.2.3
Summary: SAML2 support based on PyXB
Home-page: http://pypi.python.org/pypi/dm.xmlsec.pyxb
Author: Dieter Maurer
Author-email: dieter@handshake.de
License: BSD
Keywords: saml2 pyxb
Platform: UNKNOWN
Classifier: Development Status :: 5 - Production/Stable
Classifier: Intended Audience :: Developers
Classifier: License :: OSI Approved :: BSD License
Classifier: Operating System :: OS Independent
Classifier: Programming Language :: Python :: 2.4
Classifier: Programming Language :: Python :: 2.6
Classifier: Topic :: Utilities
